dats/__init__.py
dats/core/__init__.py
dats/core/client.py
dats/core/server.py
dats_core-0.1.0.dist-info/METADATA
dats_core-0.1.0.dist-info/RECORD
dats_core-0.1.0.dist-info/WHEEL
dats_core-0.1.0.dist-info/top_level.txt
