Metadata-Version: 2.1
Name: dats-core
Version: 0.1.0
Summary: dats core
Home-page: UNKNOWN
Author: geun young lim
Author-email: interruping4dev@gmail.com
License: UNKNOWN
Keywords: dats,datscore
Platform: UNKNOWN
Classifier: Programming Language :: Python :: 3
Classifier: Programming Language :: Python :: 3.2
Classifier: Programming Language :: Python :: 3.3
Classifier: Programming Language :: Python :: 3.4
Classifier: Programming Language :: Python :: 3.5
Classifier: Programming Language :: Python :: 3.6
Requires-Python: >=3
